odoo/addons/delivery_carrier_label_default/README.rst
odoo/addons/delivery_carrier_label_default/__init__.py
odoo/addons/delivery_carrier_label_default/__manifest__.py
odoo/addons/delivery_carrier_label_default/i18n/delivery_carrier_label_default.pot
odoo/addons/delivery_carrier_label_default/models/__init__.py
odoo/addons/delivery_carrier_label_default/models/stock.py
odoo/addons/delivery_carrier_label_default/readme/CONTRIBUTORS.rst
odoo/addons/delivery_carrier_label_default/readme/CREDITS.rst
odoo/addons/delivery_carrier_label_default/readme/DESCRIPTION.rst
odoo/addons/delivery_carrier_label_default/readme/ROADMAP.rst
odoo/addons/delivery_carrier_label_default/static/description/icon.svg
odoo/addons/delivery_carrier_label_default/static/description/index.html
odoo/addons/delivery_carrier_label_default/tests/__init__.py
odoo/addons/delivery_carrier_label_default/tests/common.py
odoo/addons/delivery_carrier_label_default/tests/test_print_label.py
odoo/addons/delivery_carrier_label_default/views/report_default_label.xml
odoo/addons/delivery_carrier_label_default/views/reports.xml
odoo11_addon_delivery_carrier_label_default-11.0.1.0.1.99.dev3.dist-info/METADATA
odoo11_addon_delivery_carrier_label_default-11.0.1.0.1.99.dev3.dist-info/WHEEL
odoo11_addon_delivery_carrier_label_default-11.0.1.0.1.99.dev3.dist-info/top_level.txt
odoo11_addon_delivery_carrier_label_default-11.0.1.0.1.99.dev3.dist-info/RECORD
