Metadata-Version: 2.1
Name: odoo11-addon-delivery-carrier-label-default
Version: 11.0.1.0.1.99.dev3
Summary: This module defines a basic label to print when no specific carrier is selected.
Home-page: https://github.com/OCA/delivery-carrier
Author: Camptocamp, Odoo Community Association (OCA)
Author-email: support@odoo-community.org
License: AGPL-3
Platform: UNKNOWN
Classifier: Programming Language :: Python
Classifier: Framework :: Odoo
Classifier: Framework :: Odoo :: 11.0
Classifier: License :: OSI Approved :: GNU Affero General Public License v3
Classifier: Development Status :: 5 - Production/Stable
Requires-Python: >=2.7, !=3.0.*, !=3.1.*, !=3.2.*, !=3.3.*, !=3.4.*
Requires-Dist: odoo11-addon-base-delivery-carrier-label
Requires-Dist: odoo <11.1dev,>=11.0a
